LICENSE
MANIFEST.in
README
setup.cfg
setup.py
docs/HISTORY.rst
docs/README.rst
docs/TODO.rst
docs/man/iori.1
src/iori/__init__.py
src/iori/command.py
src/iori/config.py
src/iori/control.py
src/iori/debootstwrap.py
src/iori/libvirtobj.py
src/iori/repo.py
src/iori.egg-info/PKG-INFO
src/iori.egg-info/SOURCES.txt
src/iori.egg-info/dependency_links.txt
src/iori.egg-info/entry_points.txt
src/iori.egg-info/requires.txt
src/iori.egg-info/top_level.txt
src/iori/tests/test__init__.py
src/iori/tests/test_control.py
src/iori/tests/test_libvirtobj.py
src/iori/tests/test_pep8.py
src/iori/tests/test_repo.py