Metadata-Version: 1.1
Name: iori
Version: 0.1.1
Summary: LXC deploy and config management tool
Home-page: https://github.com/mkouhei/iori
Author: Kouhei Maeda
Author-email: mkouhei@palmtb.net
License:  GNU General Public License version 3
Platform: UNKNOWN
Classifier: Development Status :: 3 - Alpha
Classifier: Intended Audience :: System Administrators
Classifier: License :: OSI Approved :: GNU General Public License v3 or later (GPLv3+)
Classifier: Programming Language :: Python
Classifier: Topic :: System :: Systems Administration
